fair_python_cookiecutter/__init__.py
fair_python_cookiecutter/cli.py
fair_python_cookiecutter/config.py
fair_python_cookiecutter/main.py
fair_python_cookiecutter/template/cookiecutter.json
fair_python_cookiecutter/template/post_gen_project.bat
fair_python_cookiecutter/template/{{ cookiecutter.project_slug }}/.github/ISSUE_TEMPLATE/bug_report.md
fair_python_cookiecutter/template/{{ cookiecutter.project_slug }}/.github/ISSUE_TEMPLATE/feature_request.md
fair_python_cookiecutter/template/{{ cookiecutter.project_slug }}/.github/workflows/ci.yml
fair_python_cookiecutter/template/{{ cookiecutter.project_slug }}/.github/workflows/release.yml
fair_python_cookiecutter/template/{{ cookiecutter.project_slug }}/.gitignore
fair_python_cookiecutter/template/{{ cookiecutter.project_slug }}/.gitlab/issue_templates/Default.md
fair_python_cookiecutter/template/{{ cookiecutter.project_slug }}/.gitlab-ci.yml
fair_python_cookiecutter/template/{{ cookiecutter.project_slug }}/.pre-commit-config.yaml
fair_python_cookiecutter/template/{{ cookiecutter.project_slug }}/AUTHORS.md
fair_python_cookiecutter/template/{{ cookiecutter.project_slug }}/CHANGELOG.md
fair_python_cookiecutter/template/{{ cookiecutter.project_slug }}/CITATION.cff
fair_python_cookiecutter/template/{{ cookiecutter.project_slug }}/CODE_OF_CONDUCT.md
fair_python_cookiecutter/template/{{ cookiecutter.project_slug }}/CONTRIBUTING.md
fair_python_cookiecutter/template/{{ cookiecutter.project_slug }}/README.md
fair_python_cookiecutter/template/{{ cookiecutter.project_slug }}/docs/changelog.md
fair_python_cookiecutter/template/{{ cookiecutter.project_slug }}/docs/code_of_conduct.md
fair_python_cookiecutter/template/{{ cookiecutter.project_slug }}/docs/contributing.md
fair_python_cookiecutter/template/{{ cookiecutter.project_slug }}/docs/credits.md
fair_python_cookiecutter/template/{{ cookiecutter.project_slug }}/docs/css/style.css
fair_python_cookiecutter/template/{{ cookiecutter.project_slug }}/docs/dev_guide.md
fair_python_cookiecutter-1.0.0.dist-info/AUTHORS.md
fair_python_cookiecutter-1.0.0.dist-info/LICENSE
fair_python_cookiecutter-1.0.0.dist-info/LICENSES/CC0-1.0.txt
fair_python_cookiecutter-1.0.0.dist-info/LICENSES/MIT.txt
fair_python_cookiecutter-1.0.0.dist-info/METADATA
fair_python_cookiecutter-1.0.0.dist-info/WHEEL
fair_python_cookiecutter-1.0.0.dist-info/entry_points.txt
fair_python_cookiecutter-1.0.0.dist-info/RECORD
