Metadata-Version: 2.3
Name: fair-python-cookiecutter
Version: 1.0.0
Summary: An opinionated cookiecutter template to kickstart a modern best-practice Python project with FAIR metadata.
License: MIT
Keywords: fair,metadata,python,cookiecutter,template
Author: Anton Pirogov
Author-email: a.pirogov@fz-juelich.de
Maintainer: Mustafa Soylu
Maintainer-email: m.soylu@fz-juelich.de
Requires-Python: >=3.9
Classifier: Intended Audience :: Science/Research
Classifier: Intended Audience :: Developers
Requires-Dist: cookiecutter (>=2.6.0)
Requires-Dist: importlib-metadata (>=8.6.1,<9.0.0)
Requires-Dist: importlib-resources (>=6.4.0)
Requires-Dist: platformdirs (>=4.2.2)
Requires-Dist: pydantic (>=2.8.2)
Requires-Dist: pydantic-yaml (>=1.3.0)
Requires-Dist: spdx-lookup (>=0.3.3)
Requires-Dist: typer[all] (>=0.12.3)
Requires-Dist: typing-extensions (>=4.12.2)
Project-URL: Documentation, https://materials-data-science-and-informatics.github.io/fair-python-cookiecutter
Project-URL: Homepage, https://materials-data-science-and-informatics.github.io/fair-python-cookiecutter
Project-URL: Repository, https://github.com/Materials-Data-Science-and-Informatics/fair-python-cookiecutter
